<?xml version="1.0" encoding="utf-8"?>
<odoo>
    <menuitem id="menu_nn_fund_root" name="Fund Management" sequence="10"/>

    <menuitem id="menu_nn_fund_operations" name="Operations" parent="menu_nn_fund_root" sequence="10"/>
    <menuitem id="menu_nn_fund_configuration" name="Configuration" parent="menu_nn_fund_root" sequence="20"/>

    <menuitem id="menu_nn_incoming_funds" name="Incoming Funds" parent="menu_nn_fund_operations" action="action_nn_fund_transaction" sequence="10"/>
    <menuitem id="menu_nn_fund_allocation" name="Fund Allocations" parent="menu_nn_fund_operations" action="action_nn_fund_allocation" sequence="20"/>
    <menuitem id="menu_nn_fund_requisition" name="Requisitions" parent="menu_nn_fund_operations" action="action_nn_fund_requisition" sequence="30"/>
    <menuitem id="menu_nn_fund_bill" name="Vendor Bills" parent="menu_nn_fund_operations" action="action_nn_fund_bill" sequence="40"/>
    <menuitem id="menu_nn_fund_transfer" name="Internal Transfers" parent="menu_nn_fund_operations" action="action_nn_fund_transfer" sequence="50"/>

    <menuitem id="menu_nn_fund_account" name="Fund Accounts" parent="menu_nn_fund_configuration" action="action_nn_fund_account" sequence="10"/>
</odoo>